auto_genesis_sdk/__init__.py
auto_genesis_sdk_beta-0.0.1.dist-info/METADATA
auto_genesis_sdk_beta-0.0.1.dist-info/WHEEL
auto_genesis_sdk_beta-0.0.1.dist-info/licenses/LICENSE
auto_genesis_sdk_beta-0.0.1.dist-info/RECORD
